LICENSE
MANIFEST.in
README.md
setup.py
primegapverify/__init__.py
primegapverify/_version.py
primegapverify/parsenumber.py
primegapverify/utils.py
primegapverify.egg-info/PKG-INFO
primegapverify.egg-info/SOURCES.txt
primegapverify.egg-info/dependency_links.txt
primegapverify.egg-info/top_level.txt
primegapverify/verify/primes.cpp
primegapverify/verify/primes.hpp
primegapverify/verify/sieve_util.cpp
primegapverify/verify/sieve_util.hpp
primegapverify/verify/verify.cpp
primegapverify/verify/verify.hpp
primegapverify/verify/verifymodule.cpp