Metadata-Version: 2.1
Name: primegapverify
Version: 0.11.6
Summary: Helpful tools for verifying prime gaps
Home-page: https://github.com/sethtroisi/prime-gap-verify
Author: Seth Troisi
Author-email: sethtroisi@google.com
License: Apache License 2.0
Keywords: gmp gmpy2 prime-gaps
Classifier: Development Status :: 3 - Alpha
Classifier: Intended Audience :: Developers
Classifier: Intended Audience :: Science/Research
Classifier: License :: OSI Approved :: Apache Software License
Classifier: Programming Language :: C
Classifier: Programming Language :: Python :: 3
Classifier: Operating System :: POSIX
Classifier: Topic :: Scientific/Engineering :: Mathematics
License-File: LICENSE
